nonebot_plugin_zxreport/__init__.py
nonebot_plugin_zxreport/config.py
nonebot_plugin_zxreport/data_source.py
nonebot_plugin_zxreport/mahiro_report/main.css
nonebot_plugin_zxreport/mahiro_report/main.html
nonebot_plugin_zxreport/mahiro_report/res/font/NotoSansSC-Bold.otf
nonebot_plugin_zxreport/mahiro_report/res/font/NotoSansSC-Regular.otf
nonebot_plugin_zxreport/mahiro_report/res/font/SSFangTangTi.ttf
nonebot_plugin_zxreport/mahiro_report/res/icon/60.png
nonebot_plugin_zxreport/mahiro_report/res/icon/bgm.png
nonebot_plugin_zxreport/mahiro_report/res/icon/bilibili.png
nonebot_plugin_zxreport/mahiro_report/res/icon/fish.png
nonebot_plugin_zxreport/mahiro_report/res/icon/game.png
nonebot_plugin_zxreport/mahiro_report/res/icon/hitokoto.png
nonebot_plugin_zxreport/mahiro_report/res/icon/it.png
nonebot_plugin_zxreport/mahiro_report/res/image/1.no-bg.png
nonebot_plugin_zxreport/mahiro_report/res/image/2.no-bg.png
nonebot_plugin_zxreport/mahiro_report/res/image/2.png
nonebot_plugin_zxreport/mahiro_report/res/image/bottom.png
nonebot_plugin_zxreport-0.3.3.dist-info/LICENSE
nonebot_plugin_zxreport-0.3.3.dist-info/METADATA
nonebot_plugin_zxreport-0.3.3.dist-info/WHEEL
nonebot_plugin_zxreport-0.3.3.dist-info/RECORD
