Metadata-Version: 2.1
Name: nonebot-plugin-zxreport
Version: 0.3.3
Summary: 真寻日报
Home-page: https://github.com/HibiKier/nonebot-plugin-zxreport
License: AGPL3.0
Author: HibiKier
Author-email: 775757368@qq.com
Requires-Python: >=3.10,<4.0
Classifier: License :: Other/Proprietary License
Classifier: Programming Language :: Python :: 3
Classifier: Programming Language :: Python :: 3.10
Classifier: Programming Language :: Python :: 3.11
Classifier: Programming Language :: Python :: 3.12
Requires-Dist: httpx (>=0.27.2,<0.28.0)
Requires-Dist: nonebot-plugin-alconna (>=0.46.3,<1.0.0)
Requires-Dist: nonebot-plugin-apscheduler (>=0.5.0,<0.6.0)
Requires-Dist: nonebot-plugin-htmlrender (>=0.3.5,<0.4.0)
Requires-Dist: nonebot-plugin-localstore (>=0.7.1,<0.8.0)
Requires-Dist: nonebot-plugin-uninfo (>=0.5.0,<0.6.0)
Requires-Dist: nonebot2 (>=2.3.3,<3.0.0)
Requires-Dist: tenacity (>=9.0.0,<10.0.0)
Requires-Dist: zhdate (>=0.1,<0.2)
Project-URL: Repository, https://github.com/HibiKier/nonebot-plugin-zxreport
